[
  {
    "name": "US",
    "limits": [
      {"max": 200, "uom": "mg/l", "code": "natrium" },
      {"max": 50, "uom": "mg/l", "code": "nitrate" },
      {"max": 0, "uom": "mg/l", "code": "fluoride" },
      {"max": 250, "uom": "mg/l", "code": "chloride" },
      {"max": 250, "uom": "mg/l", "code": "sulfate" }
    ],
    "sources":[
      "https://www.epa.gov/dwstandardsregulations/secondary-drinking-water-standards-guidance-nuisance-chemicals",
      "http://www.waterboards.ca.gov/drinking_water/certlic/drinkingwater/Chemicalcontaminants.shtml",
      "http://www.waterboards.ca.gov/drinking_water/certlic/drinkingwater/Documents/EDTlibrary/storlist.xls"
    ]
  },
  {
    "name": "EU",
    "limits":[
      {"max": 200, "uom": "mg/l", "code": "natrium" },
      {"max": 12, "uom": "mg/l", "code": "kalium" },
      {"max": 400, "uom": "mg/l", "code": "calcium" },
      {"max": 60, "uom": "mg/l", "code": "nitrate" },
      {"max": 60, "uom": "mg/l", "code": "magnesium" },
      {"max": 0, "uom": "mg/l", "code": "fluoride" },
      {"max": 240, "uom": "mg/l", "code": "chloride" },
      {"max": 240, "uom": "mg/l", "code": "sulfate" }
    ]
  },
  {
    "name": "NL",
    "description": "Extracted from reports by Brabant Water and Dunea, the Netherlands",
    "limits":[
      {"max": 0.2, "uom": "mg/l", "code": "aluminum" },
      {"min": 7, "max": 9.5, "uom": "pH", "code": "acidity" },
      {"max": 0.01, "uom": "mg/l", "code": "arsine" },
      {"max": 0.5, "uom": "mg/l", "code": "barium" },
      {"max": 150, "uom": "mg/l", "code": "natrium" },
      {"max": 125, "uom": "mS/m", "code": "conductance" },
      {"max": 150, "uom": "mg/l", "code": "sulfate" },
      {"max": 0.005, "uom": "mg/l", "code": "antimony" },
      {"max": 0.005, "uom": "mg/l", "code": "cadmium" },
      {"max": 0.05, "uom": "mg/l", "code": "chromium" },
      {"max": 1, "uom": "mg/l", "code": "fluoride" },
      {"max": 0.2, "uom": "mg/l", "code": "iron" },
      {"max": 150, "uom": "mg/l", "code": "chloride" },
      {"min": 60, "uom": "mg/l", "code": "bicarbonate" },
      {"max": 0.01, "uom": "mg/l", "code": "mercury" },
      {"min": 2, "uom": "mg/l", "code": "oxygen" },
      {"max": 1, "uom": "ftu", "code": "turbidity" },
      {"min": 1, "uom": "mmol/l", "code": "hardness" },
      {"max": 20, "uom": "mg/l", "code": "pt_co" },
      {"max": 0.05, "uom": "mg/l", "code": "manganese" },
      {"max": 0.2, "uom": "mg/l", "code": "ammonium" },
      {"max": 0.1, "uom": "mg/l", "code": "nitrite" },
      {"max": 50, "uom": "mg/l", "code": "nitrate" },
      {"max": 25, "uom": "degC", "code": "watertemperature" },
      {"max": 0.01, "uom": "mg/l", "code": "selenium" },
      {"min": -0.2, "uom": "ph", "code": "saturation" },
      {"min": 2, "uom": "mg/l", "code": "copper" },
      {"min": 3, "uom": "mg/l", "code": "zinc" },
      {"min": 0.05, "uom": "mg/l", "code": "cyanide" },
      {"min": 0.02, "uom": "mg/l", "code": "thrihalomethanes" },
      {"max": 0.1, "uom": "mg/l", "code": "lead" },
      {"max": 0.02, "uom": "mg/l", "code": "nickel" },
      {"max": 1000, "uom": "cfu/dl", "code": "aeromonas" },
      {"max": 0, "uom": "cfu/dl", "code": "clostridium" },
      {"max": 0, "uom": "cfu/dl", "code": "coli" },
      {"max": 0, "uom": "cfu/dl", "code": "enterococci" },
      {"max": 100, "uom": "cfu/l", "code": "legionella" }
    ]
  }
]
